docs/Enrichment.md
docs/Nql.md
docs/examples.md
docs/extra.css
docs/index.md
docs/models.md
docs/nxt_api_request.md
docs/nxt_endpoint.md
docs/nxt_invalid_token_request.md
docs/nxt_region_name.md
docs/nxt_response.md
docs/nxt_settings.md
docs/nxt_token_request.md
docs/nxt_token_response.md
nexthink_api/__init__.py
nexthink_api/_version.py
nexthink_api/Clients/__init__.py
nexthink_api/Clients/nxt_api_client.py
nexthink_api/Clients/nxt_response.py
nexthink_api/Enrichment/__init__.py
nexthink_api/Enrichment/nxt_bad_request_response.py
nexthink_api/Enrichment/nxt_enrichment.py
nexthink_api/Enrichment/nxt_enrichment_request.py
nexthink_api/Enrichment/nxt_error.py
nexthink_api/Enrichment/nxt_field.py
nexthink_api/Enrichment/nxt_field_name.py
nexthink_api/Enrichment/nxt_forbidden_response.py
nexthink_api/Enrichment/nxt_identification.py
nexthink_api/Enrichment/nxt_identification_name.py
nexthink_api/Enrichment/nxt_individual_object_error.py
nexthink_api/Enrichment/nxt_partial_success_response.py
nexthink_api/Enrichment/nxt_success_response.py
nexthink_api/Exceptions/__init__.py
nexthink_api/Exceptions/nxt_api_exception.py
nexthink_api/Exceptions/nxt_exception.py
nexthink_api/Exceptions/nxt_export_exception.py
nexthink_api/Exceptions/nxt_param_exception.py
nexthink_api/Exceptions/nxt_status_exception.py
nexthink_api/Exceptions/nxt_timeout_exception.py
nexthink_api/Exceptions/nxt_token_exception.py
nexthink_api/Models/__init__.py
nexthink_api/Models/nxt_endpoint.py
nexthink_api/Models/nxt_invalid_token_request.py
nexthink_api/Models/nxt_region_name.py
nexthink_api/Models/nxt_settings.py
nexthink_api/Models/nxt_token_request.py
nexthink_api/Models/nxt_token_response.py
nexthink_api/Nql/__init__.py
nexthink_api/Nql/nxt_date_time.py
nexthink_api/Nql/nxt_error_response.py
nexthink_api/Nql/nxt_nql_api_execute_request.py
nexthink_api/Nql/nxt_nql_api_execute_response.py
nexthink_api/Nql/nxt_nql_api_execute_v2_response.py
nexthink_api/Nql/nxt_nql_api_export_response.py
nexthink_api-0.0.8.dist-info/LICENSE
nexthink_api-0.0.8.dist-info/METADATA
nexthink_api-0.0.8.dist-info/WHEEL
nexthink_api-0.0.8.dist-info/top_level.txt
nexthink_api-0.0.8.dist-info/RECORD
