Metadata-Version: 2.1
Name: nexthink_api
Version: 0.0.8
Summary: Python package for Nexthink API
Author-email: Laurent Taupiac <ltaupiac@lfdj.com>
License: GNU GENERAL PUBLIC LICENSE
Project-URL: Documentation, https://developer.nexthink.com/docs/api/
Keywords: nexthink,nql,enrichment
Classifier: License :: OSI Approved :: MIT License
Requires-Python: >=3.10
License-File: LICENSE
Requires-Dist: requests ==2.31.0
Requires-Dist: urllib3
Requires-Dist: pydantic
Requires-Dist: pyyaml
